varbio/__init__.py
varbio/clean.py
varbio/correlation.py
varbio/parse.py
varbio/tests/__init__.py
varbio/tests/conftest.py
varbio/tests/test_clean.py
varbio/tests/test_correlation.py
varbio/tests/test_parse.py
varbio-2.0.0.dist-info/DESCRIPTION.rst
varbio-2.0.0.dist-info/METADATA
varbio-2.0.0.dist-info/RECORD
varbio-2.0.0.dist-info/WHEEL
varbio-2.0.0.dist-info/metadata.json
varbio-2.0.0.dist-info/top_level.txt
